mosaicqueen/__init__.py
mosaicqueen/main.py
mosaicqueen/make_mosaic.py
mosaic_queen-2.0.2.dist-info/LICENSE
mosaic_queen-2.0.2.dist-info/METADATA
mosaic_queen-2.0.2.dist-info/WHEEL
mosaic_queen-2.0.2.dist-info/entry_points.txt
mosaic_queen-2.0.2.dist-info/RECORD
