Metadata-Version: 2.1
Name: mosaic-queen
Version: 2.0.2
Summary: For making astronomy image mosaics using montage
License: GNU GPL v2
Author: Sarah White
Author-email: sarahwhite.astro@gmail.com
Requires-Python: >=3.9,<3.13
Classifier: License :: Other/Proprietary License
Classifier: Programming Language :: Python :: 3
Classifier: Programming Language :: Python :: 3.9
Classifier: Programming Language :: Python :: 3.10
Classifier: Programming Language :: Python :: 3.11
Classifier: Programming Language :: Python :: 3.12
Requires-Dist: astropy
Requires-Dist: matplotlib
Requires-Dist: memory-profiler
Requires-Dist: numpy (<2.0)
Requires-Dist: scipy
